text2py/__init__.py
text2py/parser.py
text2py/run.py
text2py/runner.py
text2py-0.0.2.dist-info/LICENSE
text2py-0.0.2.dist-info/METADATA
text2py-0.0.2.dist-info/WHEEL
text2py-0.0.2.dist-info/entry_points.txt
text2py-0.0.2.dist-info/top_level.txt
text2py-0.0.2.dist-info/RECORD
