Metadata-Version: 2.1
Name: text2py
Version: 0.0.2
Summary: Library for processing structured text into python object (dict or list) using templates
Home-page: https://gitlab.com/omaxx/text2py
Author: maxim orlov
Author-email: maxx.orlov@gmail.com
License: MIT License
Platform: UNKNOWN
Classifier: Development Status :: 3 - Alpha
Classifier: Programming Language :: Python :: 3
Classifier: Programming Language :: Python :: 3.5
Classifier: Programming Language :: Python :: 3.6
Classifier: Programming Language :: Python :: 3.7
Classifier: License :: OSI Approved :: MIT License
Classifier: Operating System :: OS Independent
Requires-Python: >=3.5
Requires-Dist: PyYAML
